MANIFEST.in
README.rst
setup.py
django_easy_app/__init__.py
django_easy_app/appmanager.py
django_easy_app/package_metadata.json
django_easy_app/urlmanager.py
django_easy_app.egg-info/PKG-INFO
django_easy_app.egg-info/SOURCES.txt
django_easy_app.egg-info/dependency_links.txt
django_easy_app.egg-info/requires.txt
django_easy_app.egg-info/top_level.txt
django_easy_app/management/__init__.py
django_easy_app/management/commands/__init__.py
django_easy_app/management/commands/starteasyapp.py
scripts/django_easy